puppet_enc_common/__init__.py
puppet_enc_common/constants.py
puppet_enc_common/database.py
puppet_enc_common/globals.py
puppet_enc_common-0.0.12.dist-info/LICENSE.txt
puppet_enc_common-0.0.12.dist-info/METADATA
puppet_enc_common-0.0.12.dist-info/WHEEL
puppet_enc_common-0.0.12.dist-info/top_level.txt
puppet_enc_common-0.0.12.dist-info/RECORD
