Metadata-Version: 2.1
Name: puppet-enc-common
Version: 0.0.12
Summary: Puppet ENC Common Elements
Home-page: https://github.com/graham-m-smith/puppet-enc-common-python-module
Maintainer: Graham Smith
Maintainer-email: github@gmsnet.co.uk
License: MIT
Classifier: Development Status :: 4 - Beta
Classifier: Framework :: Flask
Classifier: License :: OSI Approved :: MIT License
Classifier: Operating System :: OS Independent
Classifier: Programming Language :: Python :: 3
License-File: LICENSE.txt
Requires-Dist: peewee
Requires-Dist: Werkzeug
Requires-Dist: Flask-Login
